README.txt
setup.cfg
setup.py
Products/__init__.py
Products.PloneTableless.egg-info/PKG-INFO
Products.PloneTableless.egg-info/SOURCES.txt
Products.PloneTableless.egg-info/dependency_links.txt
Products.PloneTableless.egg-info/entry_points.txt
Products.PloneTableless.egg-info/namespace_packages.txt
Products.PloneTableless.egg-info/not-zip-safe
Products.PloneTableless.egg-info/paster_plugins.txt
Products.PloneTableless.egg-info/requires.txt
Products.PloneTableless.egg-info/top_level.txt
Products/PloneTableless/CHANGES.txt
Products/PloneTableless/README.txt
Products/PloneTableless/__init__.py
Products/PloneTableless/configure.zcml
Products/PloneTableless/profiles.zcml
Products/PloneTableless/skins.zcml
Products/PloneTableless/version.txt
Products/PloneTableless/Extensions/Install.py
Products/PloneTableless/Extensions/__init__.py
Products/PloneTableless/profiles/default/metadata.xml
Products/PloneTableless/profiles/default/skins.xml
Products/PloneTableless/profiles/uninstall/metadata.xml
Products/PloneTableless/profiles/uninstall/skins.xml
Products/PloneTableless/skins/plone_tableless/IEFixes.css.dtml
Products/PloneTableless/skins/plone_tableless/IEFixes.css.dtml.metadata
Products/PloneTableless/skins/plone_tableless/columns.css.dtml
Products/PloneTableless/skins/plone_tableless/columns.css.dtml.metadata
Products/PloneTableless/skins/plone_tableless/hide_columns.js
Products/PloneTableless/skins/plone_tableless/main_template.pt
Products/PloneTableless/skins/plone_tableless/prefs_main_template.pt
Products/PloneTableless/skins/plone_tableless/prefs_main_template.pt.metadata
docs/HISTORY.txt
docs/INSTALL.txt
docs/LICENSE.GPL
docs/LICENSE.txt