Metadata-Version: 1.0
Name: Products.PloneTableless
Version: 1.2
Summary: Plone Tableless provides a completly tableless version of the Plone Default theme
Home-page: http://plone.org/products/plone-tableless
Author: Raptus AG (Simon Kaeser)
Author-email: skaeser@raptus.com
License: GPL
Keywords: plone theme tableless
Platform: UNKNOWN
Classifier: Framework :: Plone
Classifier: Programming Language :: Python
Classifier: Topic :: Software Development :: Libraries :: Python Modules
